TheCoolFunctions/__init__.py
TheCoolFunctions/function1.py
TheCoolFunctions/function2.py
coolfunctioncoolcool-0.0.3.dist-info/METADATA
coolfunctioncoolcool-0.0.3.dist-info/WHEEL
coolfunctioncoolcool-0.0.3.dist-info/top_level.txt
coolfunctioncoolcool-0.0.3.dist-info/RECORD
