Metadata-Version: 2.1
Name: coolfunctioncoolcool
Version: 0.0.3
Summary: Say hello!
Home-page: UNKNOWN
Author: RaphaelKalfon
Author-email: raphaelkalfon9@gmail.com
License: UNKNOWN
Keywords: python
Platform: UNKNOWN
